metadata_logger/__init__.py
metadata_logger/_version.py
metadata_logger/metadata_logger.py
metadata_logger-0.1.0.dev0.dist-info/LICENSE
metadata_logger-0.1.0.dev0.dist-info/METADATA
metadata_logger-0.1.0.dev0.dist-info/WHEEL
metadata_logger-0.1.0.dev0.dist-info/top_level.txt
metadata_logger-0.1.0.dev0.dist-info/zip-safe
metadata_logger-0.1.0.dev0.dist-info/RECORD
